[
    {
        "Ebenezer": 254,
        "Dorset": 254,
        "Bill": 164,
        "Driscoll": 124,
        "'s": 52,
        "Sam": 26,
        "Hank": 9,
        "\u00d3": 8,
        "the": 6,
        "O.": 4,
        "HENRY": 4,
        "Old": 4,
        "Trapper": 3,
        "?": 3,
        "i.": 2,
        "David": 2,
        "I\u00d5ll": 2,
        "Black": 2,
        "Scout": 2,
        "Ransom": 1,
        "of": 1,
        "Red": 1,
        "Chief": 1,
        "I\u00d5m": 1,
        "Geronimo": 1,
        "snake": 1,
        "-": 1,
        "eye": 1,
        "Jimmy": 1,
        "Talbot": 1,
        "Ed": 1,
        "Walker": 1,
        "Amo": 1,
        "Murray": 1,
        "\u00d2We\u00d5ll": 1,
        "Jane": 1,
        "Goliath": 1,
        "\u00d2King": 1,
        "Herod": 1,
        "Summit": 1,
        "We\u00d5ve": 1,
        "we\u00f5ll": 1
    },
    {
        "Edgar": 170,
        "Allan": 170,
        "Poe": 166,
        "'s": 25,
        "poe": 4,
        "this": 2,
        "Madmen": 1,
        "evil": 1,
        "Eye": 1,
        "death": 1,
        "I": 1
    },
    {
        "Frank": 1,
        "R.": 1,
        "Stockton": 1
    },
    {
        "Jig": 6,
        "Ernest": 1,
        "Hemingway": 1,
        "American'm": 1
    },
    {
        "Leiningen": 303,
        "Macbeth": 3,
        "Carl": 1,
        "Stephenson": 1,
        "Hood": 1,
        "Pell": 1,
        "-": 1,
        "mell": 1,
        "Dawn": 1,
        "Birnam": 1,
        "Wood": 1,
        "Dante": 1,
        "Spry": 1,
        "Swift": 1
    },
    {
        "Della": 144,
        "Jim": 99,
        "James": 12,
        "Dillingham": 11,
        "Young": 11,
        "Combs": 8,
        "'s": 4,
        "the": 3,
        "\u00d3": 3,
        "of": 3,
        "gift": 1,
        "Magi": 1,
        "D.": 1,
        "I\u00d5m": 1,
        ",": 1,
        "Christ": 1,
        "-": 1,
        "child": 1
    },
    {
        "Rain": 749,
        "Zaroff": 55,
        "Whitney": 19,
        "Cossack": 12,
        "Ivan": 8,
        "the": 4,
        "Lazarus": 3,
        "'s": 3,
        "Sanger": 2,
        "Richard": 1,
        "Connell": 1,
        "Nielsen": 1,
        "Ennui": 1,
        "Suzette": 1,
        "Dusk": 1,
        "Marcus": 1,
        "Aurelius": 1
    }
]